warrenapp/__init__.py
warrenapp/apps.py
warrenapp/models.py
warrenapp/badelf_tools/acf.py
warrenapp/badelf_tools/badelf_algorithm_functions.py
warrenapp/badelf_tools/utilities.py
warrenapp/inputs/warren_potcar_mappings.py
warrenapp/workflows/__init__.py
warrenapp/workflows/nested_dft/__init__.py
warrenapp/workflows/nested_dft/double_relaxation_static_base.py
warrenapp/workflows/nested_dft/prepop_relaxation_static_hse_hse.py
warrenapp/workflows/nested_dft/prepop_relaxation_static_pbesol_hse.py
warrenapp/workflows/nested_dft/prepop_relaxation_static_pbesol_hse_hse.py
warrenapp/workflows/nested_dft/prepop_relaxation_static_pbesol_pbesol.py
warrenapp/workflows/nested_dft/relaxation_static_base.py
warrenapp/workflows/population_analysis/__init__.py
warrenapp/workflows/population_analysis/badelf_hse.py
warrenapp/workflows/population_analysis/badelf_pbesol.py
warrenapp/workflows/population_analysis/bader_badelf.py
warrenapp/workflows/population_analysis/bader_badelf_hse.py
warrenapp/workflows/population_analysis/bader_badelf_pbesol.py
warrenapp/workflows/population_analysis/bader_badelf_wrap.py
warrenapp/workflows/population_analysis/bader_hse.py
warrenapp/workflows/population_analysis/bader_pbesol.py
warrenapp/workflows/population_analysis/base.py
warrenapp/workflows/population_analysis/elf_hse.py
warrenapp/workflows/population_analysis/elf_pbesol.py
warrenapp/workflows/population_analysis/prebader_badelf_dft.py
warrenapp/workflows/population_analysis/warren_badelf_v3_9.py
warrenapp/workflows/relaxation/__init__.py
warrenapp/workflows/relaxation/hse.py
warrenapp/workflows/relaxation/hsesol.py
warrenapp/workflows/relaxation/pbe.py
warrenapp/workflows/relaxation/pbe_metal.py
warrenapp/workflows/relaxation/pbesol.py
warrenapp/workflows/relaxation/scan.py
warrenapp/workflows/static_energy/__init__.py
warrenapp/workflows/static_energy/hse.py
warrenapp/workflows/static_energy/hsesol.py
warrenapp/workflows/static_energy/pbe.py
warrenapp/workflows/static_energy/pbe_metal.py
warrenapp-0.2.0.dist-info/LICENSE
warrenapp-0.2.0.dist-info/METADATA
warrenapp-0.2.0.dist-info/WHEEL
warrenapp-0.2.0.dist-info/top_level.txt
warrenapp-0.2.0.dist-info/RECORD
