Metadata-Version: 2.1
Name: warrenapp
Version: 0.2.0
Summary: The Warrenapp is an extension of the Simulated Materials Ecosystem (Simmate), a package designed to ease computational materials research. The WarrenApp adds several custom workflows and settings.
Author-email: Sam Weaver <sweav@unc.edu>
License: BSD 3-Clause License
Project-URL: Homepage, https://github.com/SWeav02/warrenapp
Requires-Python: >=3.10
License-File: LICENSE
Requires-Dist: simmate
